model_templates/__init__.py
model_templates/base_templates.yaml
model_templates/CNS_2019_Tutorial/templates.yaml
model_templates/neural_mass_models/__init__.py
model_templates/neural_mass_models/ik.yaml
model_templates/neural_mass_models/jansenrit.yaml
model_templates/neural_mass_models/qif.yaml
model_templates/neural_mass_models/synaptic_plasticity.yaml
model_templates/neural_mass_models/theta.yaml
model_templates/neural_mass_models/wilsoncowan.yaml
model_templates/oscillators/__init__.py
model_templates/oscillators/kuramoto.yaml
model_templates/oscillators/stuartlandau.yaml
model_templates/oscillators/vanderpol.yaml
model_templates/test_resources/__init__.py
model_templates/test_resources/linear.yaml
model_templates/test_resources/test_backend.yaml
model_templates/test_resources/test_operator_caching_templates.yml
pyrates/__init__.py
pyrates/utility.py
pyrates/backend/__init__.py
pyrates/backend/computegraph.py
pyrates/backend/parser.py
pyrates/backend/base/__init__.py
pyrates/backend/base/base_backend.py
pyrates/backend/base/base_funcs.py
pyrates/backend/fortran/__init__.py
pyrates/backend/fortran/fortran_backend.py
pyrates/backend/fortran/fortran_funcs.py
pyrates/backend/julia/__init__.py
pyrates/backend/julia/julia_backend.py
pyrates/backend/julia/julia_funcs.py
pyrates/backend/matlab/__init__.py
pyrates/backend/matlab/matlab_backend.py
pyrates/backend/matlab/matlab_funcs.py
pyrates/backend/tensorflow/__init__.py
pyrates/backend/tensorflow/tensorflow_backend.py
pyrates/backend/tensorflow/tensorflow_funcs.py
pyrates/backend/torch/__init__.py
pyrates/backend/torch/torch_backend.py
pyrates/backend/torch/torch_funcs.py
pyrates/frontend/__init__.py
pyrates/frontend/dict.py
pyrates/frontend/file.py
pyrates/frontend/fileio/__init__.py
pyrates/frontend/fileio/pickle.py
pyrates/frontend/fileio/yaml.py
pyrates/frontend/template/__init__.py
pyrates/frontend/template/_io.py
pyrates/frontend/template/abc.py
pyrates/frontend/template/circuit.py
pyrates-1.0.9.dist-info/LICENSE
pyrates-1.0.9.dist-info/METADATA
pyrates-1.0.9.dist-info/WHEEL
pyrates-1.0.9.dist-info/top_level.txt
pyrates-1.0.9.dist-info/RECORD
