Metadata-Version: 2.1
Name: pyrates
Version: 1.0.9
Summary: Dynamical Systems Modeling Framework
Home-page: UNKNOWN
Author: Richard Gast, Daniel Rose
Author-email: rgast@scripps.edu
License: GPL v3
Platform: UNKNOWN
Classifier: Programming Language :: Python :: 3
Classifier: Programming Language :: Python :: 3.8
Classifier: Programming Language :: Python :: 3.9
Classifier: Programming Language :: Python :: 3.10
Classifier: Programming Language :: Python :: 3.11
Classifier: Programming Language :: Python :: 3.12
Classifier: License :: OSI Approved :: GNU General Public License v3 (GPLv3)
Classifier: Operating System :: OS Independent
Classifier: Development Status :: 5 - Production/Stable
Classifier: Intended Audience :: Developers
Classifier: Intended Audience :: Science/Research
Classifier: Topic :: Scientific/Engineering
Requires-Python: >=3.8
Requires-Dist: numpy
Requires-Dist: networkx
Requires-Dist: pandas
Requires-Dist: ruamel.yaml
Requires-Dist: sympy
Requires-Dist: scipy
Provides-Extra: all
Requires-Dist: tensorflow>=2.0; extra == "all"
Requires-Dist: torch; extra == "all"
Requires-Dist: pytest; extra == "all"
Requires-Dist: bump2version; extra == "all"
Provides-Extra: backends
Requires-Dist: tensorflow>=2.0; extra == "backends"
Requires-Dist: torch; extra == "backends"
Provides-Extra: dev
Requires-Dist: pytest; extra == "dev"
Requires-Dist: bump2version; extra == "dev"
Provides-Extra: tests
Requires-Dist: tensorflow>=2.0; extra == "tests"
Requires-Dist: torch; extra == "tests"
Requires-Dist: pytest; extra == "tests"
Requires-Dist: bump2version; extra == "tests"
